cc_pathlib/__init__.py
cc_pathlib/case.py
cc_pathlib/path.py
cc_pathlib/uniw.py
cc_pathlib/filter/__init__.py
cc_pathlib/filter/cc_array.py
cc_pathlib/filter/cc_json.py
cc_pathlib/filter/cc_numpy.py
cc_pathlib/filter/cc_pickle.py
cc_pathlib/filter/tsv.py
cc_pathlib/tool/__init__.py
cc_pathlib/tool/dedup.py
cc_pathlib-0.1.0.dist-info/LICENSE
cc_pathlib-0.1.0.dist-info/METADATA
cc_pathlib-0.1.0.dist-info/WHEEL
cc_pathlib-0.1.0.dist-info/top_level.txt
cc_pathlib-0.1.0.dist-info/RECORD
