Metadata-Version: 2.1
Name: cc-pathlib
Version: 0.1.0
Summary: a supercharged implementation of pathlib.Path()
Home-page: https://github.com/yota-code/cc_pathlib.git
Author: Yoochan
Author-email: yota.news@gmail.com
Classifier: Programming Language :: Python :: 3
Classifier: Development Status :: 4 - Beta
Classifier: License :: OSI Approved :: BSD License
Classifier: License :: OSI Approved :: GNU General Public License v3 or later (GPLv3+)
Classifier: Operating System :: OS Independent
Requires-Python: >=3.8
License-File: LICENSE
Requires-Dist: brotli
